{
  "targets": [
    {
      "name": "ORF1a",
      "start": 266,
      "end": 13483
    },
    {
      "name": "ORF1b",
      "start": 13768,
      "end": 21555
    },
    {
      "name": "S",
      "start": 21563,
      "end": 25384
    },
    {
      "name": "3a",
      "start": 25393,
      "end": 26220
    },
    {
      "name": "E",
      "start": 26245,
      "end": 26472
    },
    {
      "name": "M",
      "start": 26523,
      "end": 27191
    },
    {
      "name": "6",
      "start": 27202,
      "end": 27387
    },
    {
      "name": "7a",
      "start": 27394,
      "end": 27759
    },
    {
      "name": "7b",
      "start": 27756,
      "end": 27887
    },
    {
      "name": "8",
      "start": 27894,
      "end": 28259
    },
    {
      "name": "N",
      "start": 28274,
      "end": 29533
    },
    {
      "name": "10",
      "start": 29558,
      "end": 29674
    }
  ]
}